google/__init__.py
google/protobuf/__init__.py
google/protobuf/descriptor.py
google/protobuf/descriptor_database.py
google/protobuf/descriptor_pb2.py
google/protobuf/descriptor_pool.py
google/protobuf/message.py
google/protobuf/message_factory.py
google/protobuf/reflection.py
google/protobuf/service.py
google/protobuf/service_reflection.py
google/protobuf/text_format.py
google/protobuf/unittest_custom_options_pb2.py
google/protobuf/unittest_import_pb2.py
google/protobuf/unittest_import_public_pb2.py
google/protobuf/unittest_mset_pb2.py
google/protobuf/unittest_no_generic_services_pb2.py
google/protobuf/unittest_pb2.py
google/protobuf/compiler/__init__.py
google/protobuf/compiler/plugin_pb2.py
google/protobuf/internal/__init__.py
google/protobuf/internal/api_implementation.py
google/protobuf/internal/containers.py
google/protobuf/internal/cpp_message.py
google/protobuf/internal/decoder.py
google/protobuf/internal/descriptor_database_test.py
google/protobuf/internal/descriptor_pool_test.py
google/protobuf/internal/descriptor_test.py
google/protobuf/internal/encoder.py
google/protobuf/internal/enum_type_wrapper.py
google/protobuf/internal/factory_test1_pb2.py
google/protobuf/internal/factory_test2_pb2.py
google/protobuf/internal/generator_test.py
google/protobuf/internal/message_cpp_test.py
google/protobuf/internal/message_factory_test.py
google/protobuf/internal/message_listener.py
google/protobuf/internal/message_test.py
google/protobuf/internal/more_extensions_dynamic_pb2.py
google/protobuf/internal/more_extensions_pb2.py
google/protobuf/internal/more_messages_pb2.py
google/protobuf/internal/python_message.py
google/protobuf/internal/reflection_cpp_generated_test.py
google/protobuf/internal/reflection_test.py
google/protobuf/internal/service_reflection_test.py
google/protobuf/internal/test_bad_identifiers_pb2.py
google/protobuf/internal/test_util.py
google/protobuf/internal/text_format_test.py
igetui-4.0.3.dist-info/DESCRIPTION.rst
igetui-4.0.3.dist-info/METADATA
igetui-4.0.3.dist-info/metadata.json
igetui-4.0.3.dist-info/pbr.json
igetui-4.0.3.dist-info/RECORD
igetui-4.0.3.dist-info/top_level.txt
igetui-4.0.3.dist-info/WHEEL
