Metadata-Version: 2.0
Name: igetui
Version: 4.0.3
Summary: igetui offical python sdk
Home-page: http://github.com/alphapigger/igetui
Author: alphapigger
Author-email: steven.hl.0901@gmail.com
License: MIT License
Keywords: igetui push
Platform: UNKNOWN
